torchmanager/__init__.py
torchmanager/basic.py
torchmanager/callbacks/__init__.py
torchmanager/callbacks/callback.py
torchmanager/callbacks/ckpt.py
torchmanager/callbacks/dynamic.py
torchmanager/callbacks/early_stop.py
torchmanager/callbacks/experiment.py
torchmanager/callbacks/lr.py
torchmanager/callbacks/tensorboard.py
torchmanager/compatibility.py
torchmanager/configs/__init__.py
torchmanager/configs/basic.py
torchmanager/data/__init__.py
torchmanager/data/dataset.py
torchmanager/data/sliding.py
torchmanager/losses/__init__.py
torchmanager/losses/cross_entropy.py
torchmanager/losses/dice.py
torchmanager/losses/loss.py
torchmanager/losses/mse.py
torchmanager/metrics/__init__.py
torchmanager/metrics/accuracy.py
torchmanager/metrics/conf_met.py
torchmanager/metrics/extractor.py
torchmanager/metrics/iou.py
torchmanager/metrics/metric.py
torchmanager/metrics/similarity.py
torchmanager/testing.py
torchmanager/train/__init__.py
torchmanager/train/checkpoint.py
torchmanager/train/learning_rate.py
torchmanager/training.py
torchmanager_core/__init__.py
torchmanager_core/checkpoint/__init__.py
torchmanager_core/checkpoint/ckpt.py
torchmanager_core/devices/__init__.py
torchmanager_core/devices/device.py
torchmanager_core/devices/protocols.py
torchmanager_core/errors/__init__.py
torchmanager_core/errors/runtime.py
torchmanager_core/errors/train.py
torchmanager_core/protocols.py
torchmanager_core/random/__init__.py
torchmanager_core/random/seed.py
torchmanager_core/typing.py
torchmanager_core/version.py
torchmanager_core/view/__init__.py
torchmanager_core/view/protocols.py
torchmanager_nightly-1.3a1.dist-info/LICENSE
torchmanager_nightly-1.3a1.dist-info/METADATA
torchmanager_nightly-1.3a1.dist-info/WHEEL
torchmanager_nightly-1.3a1.dist-info/RECORD
