Metadata-Version: 2.1
Name: torchmanager-nightly
Version: 1.3a1
Summary: PyTorch Training Manager v1.3 (Alpha 1)
Home-page: https://github.com/kisonho/torchmanager.git
Author: Qisheng He
Author-email: Qisheng.He@wayne.edu
Requires-Python: >=3.9,<4.0
Classifier: Programming Language :: Python :: 3
Classifier: Programming Language :: Python :: 3.9
Classifier: Programming Language :: Python :: 3.10
Classifier: Programming Language :: Python :: 3.11
Provides-Extra: all
Provides-Extra: scipy
Provides-Extra: tensorboard
Requires-Dist: torch
Requires-Dist: tqdm
Project-URL: Repository, https://github.com/kisonho/torchmanager.git
